hivecraft/__init__.py
hivecraft/__main__.py
hivecraft/alghive.py
hivecraft/ressources.py
hivecraft/version.py
hivecraft/prompts/__init__.py
hivecraft/prompts/cipher_prompt.py
hivecraft/prompts/obscure_prompt.py
hivecraft/prompts/prompt_file.py
hivecraft/props/__init__.py
hivecraft/props/field_definition.py
hivecraft/props/desc/descprops.py
hivecraft/props/desc/fields.py
hivecraft/props/desc/validators.py
hivecraft/props/meta/fields.py
hivecraft/props/meta/metaprops.py
hivecraft/props/meta/validators.py
hivecraft/scripts/__init__.py
hivecraft/scripts/decrypt_script.py
hivecraft/scripts/executable_script.py
hivecraft/scripts/forge_script.py
hivecraft/scripts/unveil_script.py
hivecraft-1.0.6.dist-info/licenses/LICENSE
hivecraft-1.0.6.dist-info/METADATA
hivecraft-1.0.6.dist-info/WHEEL
hivecraft-1.0.6.dist-info/entry_points.txt
hivecraft-1.0.6.dist-info/top_level.txt
hivecraft-1.0.6.dist-info/RECORD
